afrotranslate/__init__.py
afrotranslate/links_models.csv
afrotranslate/translator.py
AfroTranslate-0.0.6.dist-info/LICENCE
AfroTranslate-0.0.6.dist-info/METADATA
AfroTranslate-0.0.6.dist-info/NOTICE
AfroTranslate-0.0.6.dist-info/WHEEL
AfroTranslate-0.0.6.dist-info/top_level.txt
AfroTranslate-0.0.6.dist-info/RECORD
