Metadata-Version: 2.1
Name: AfroTranslate
Version: 0.0.6
Summary: This package allows you to obtain translations from Masakhane JoeyNMT based models. Masakhane is a grassroots research community aiming to revive and strengthen African languages through AI.
Home-page: https://github.com/hgilles06/AfroTranslate
Author: Gilles HACHEME
Author-email: gilles.hacheme@ai4innov.com
License: UNKNOWN
Platform: UNKNOWN
Classifier: Development Status :: 3 - Alpha
Classifier: License :: OSI Approved :: MIT License
Classifier: Programming Language :: Python :: 3
Requires-Python: >=3.6
License-File: LICENCE
License-File: NOTICE
Requires-Dist: joeynmt (==1.3)
Requires-Dist: googledrivedownloader (==0.4)
Requires-Dist: spacy (==3.2.1)
